<?xml version="1.0" encoding="UTF-8"?>
<!--
  #%L
  ActivityInfo Server
  %%
  Copyright (C) 2009 - 2013 UNICEF
  %%
  This program is free software: you can redistribute it and/or modify
  it under the terms of the GNU General Public License as
  published by the Free Software Foundation, either version 3 of the
  License, or (at your option) any later version.

  This program is distributed in the hope that it will be useful,
  but WITHOUT ANY WARRANTY; without even the implied warranty of
  MERCHANTABILITY or FITNESS FOR A PARTICULAR PURPOSE.  See the
  GNU General Public License for more details.

  You should have received a copy of the GNU General Public
  License along with this program.  If not, see
  <http://www.gnu.org/licenses/gpl-3.0.html>.
  #L%
  -->

<databaseChangeLog xmlns="http://www.liquibase.org/xml/ns/dbchangelog"
                   xmlns:xsi="http://www.w3.org/2001/XMLSchema-instance"
                   xsi:schemaLocation="http://www.liquibase.org/xml/ns/dbchangelog http://www.liquibase.org/xml/ns/dbchangelog/dbchangelog-2.0.xsd">

    <changeSet author="alex" id="042-10">
        <createTable tableName="folder">
            <column autoIncrement="true" name="folderId" type="INT">
                <constraints nullable="false" primaryKey="true"/>
            </column>
            <column name="name" type="VARCHAR(255)">
                <constraints nullable="false"/>
            </column>
            <column name="databaseId" type="INT">
                <constraints nullable="false"/>
            </column>
        </createTable>
    </changeSet>
    <changeSet author="alex" id="042-11">
        <sql>
            INSERT IGNORE INTO folder (databaseid, name)
            SELECT DISTINCT databaseid, category name FROM activity WHERE category IS NOT NULL
        </sql>
    </changeSet>
    <changeSet author="alex" id="042-14">
        <addColumn tableName="activity">
            <column name="folderId" type="int"/>
        </addColumn>
    </changeSet>
    <changeSet author="alex" id="042-13">
        <sql>
            UPDATE activity a
            LEFT JOIN folder f ON
            a.databaseId = f.databaseId AND
            a.category = f.name
            SET
            a.folderId = f.folderId
        </sql>
    </changeSet>
    <changeSet author="alex" id="042-14">
        <comment>Add a JSON-encoded permissions model that can be more flexible.</comment>
        <addColumn tableName="userpermission">
            <column name="model" type="longtext"/>
        </addColumn>
    </changeSet>
</databaseChangeLog>
